{
	"sponsors": [
		
		{
			"name": "Carreer Launcher",
			"description": "",
			"imageUrl": "https://svitprakarsh.github.io/PrakarshGraphics/sponsors/cl.webp",
			"websiteUrl": "http://www.careerlauncher.com/"
		},
		{
			"name": "Change Vadodara Campaign",
			"description": "",
			"imageUrl": "https://svitprakarsh.github.io/PrakarshGraphics/sponsors/cvc.webp",
			"websiteUrl": "http://www.cvc.org.in"
		},
		{
			"name": "Feelings Multimedia",
			"description": "",
			"imageUrl": "https://svitprakarsh.github.io/PrakarshGraphics/sponsors/feelings.webp",
			"websiteUrl": "https://www.feelingsmultimedia.com/"
		},
		{
			"name": "Indian Space Research Organization",
			"description": "",
			"imageUrl": "https://svitprakarsh.github.io/PrakarshGraphics/sponsors/isro.webp",
			"websiteUrl": "https://www.isro.gov.in/"
		},
		{
			"name": "Kapital Bakers",
			"description": "",
			"imageUrl": "https://svitprakarsh.github.io/PrakarshGraphics/sponsors/kapitalbakers.webp",
			"websiteUrl": ""
		},
		{
			"name": "Khushi Ambient Media Agency",
			"description": "",
			"imageUrl": "https://svitprakarsh.github.io/PrakarshGraphics/sponsors/khushimedia.webp",
			"websiteUrl": "http://khushiadvertising.com/"
		},
		{
			"name": "Renaissance Educare",
			"description": "",
			"imageUrl": "https://svitprakarsh.github.io/PrakarshGraphics/sponsors/renaissance.webp",
			"websiteUrl": "http://therenaissance.co.in/"
		},
		{
			"name": "The Gate Academy",
			"description": "",
			"imageUrl": "https://svitprakarsh.github.io/PrakarshGraphics/sponsors/thegateacademy.webp",
			"websiteUrl": "http://thegateacademy.com/"
		},
		{
			"name": "Blue Hat",
			"description": "",
			"imageUrl": "https://svitprakarsh.github.io/PrakarshGraphics/sponsors/bluehat.webp",
			"websiteUrl": ""
		},
		{
			"name": "Dry State Tonic",
			"description": "",
			"imageUrl": "https://svitprakarsh.github.io/PrakarshGraphics/sponsors/dst.webp",
			"websiteUrl": "https://www.facebook.com/pg/DST-Dry-State-Tonic-159829197972279/about/"
		},
		{
			"name": "International Dental Clinic",
			"description": "",
			"imageUrl": "https://svitprakarsh.github.io/PrakarshGraphics/sponsors/idc.webp",
			"websiteUrl": ""
		},
		{
			"name": "Kamyani Couture",
			"description": "",
			"imageUrl": "https://svitprakarsh.github.io/PrakarshGraphics/sponsors/kamyani.webp",
			"websiteUrl": ""
		},
		{
			"name": "Loksabha Jansatta",
			"description": "",
			"imageUrl": "https://svitprakarsh.github.io/PrakarshGraphics/sponsors/lsj.webp",
			"websiteUrl": ""
		},
		
		{
			"name": "Status Resturant",
			"description": "",
			"imageUrl": "https://svitprakarsh.github.io/PrakarshGraphics/sponsors/statsu.webp",
			"websiteUrl": "https://www.zomato.com/vadodara/status-restaurant-banquet-subhanpura"
		},
		{
			"name": "The Mocktail Brewery",
			"description": "",
			"imageUrl": "https://svitprakarsh.github.io/PrakarshGraphics/sponsors/tmb.webp",
			"websiteUrl": "https://www.zomato.com/vadodara/the-mocktail-brewery-alkapuri"
		},
		{
			"name": "ICICI Bank",
			"description": "",
			"imageUrl": "https://svitprakarsh.github.io/PrakarshGraphics/sponsors/icicibank.webp",
			"websiteUrl": "https://www.icicibank.com/"
		},
		{
			"name": "Green Advertisers",
			"description": "",
			"imageUrl": "https://svitprakarsh.github.io/PrakarshGraphics/sponsors/greenadvertisers.webp",
			"websiteUrl": ""
		},
		{
			"name": "Radio City 91.1FM",
			"description": "",
			"imageUrl": "https://svitprakarsh.github.io/PrakarshGraphics/sponsors/radiocity.webp",
			"websiteUrl": "http://www.radiocity.in/"
		},
		{
			"name": "White House",
			"description": "",
			"imageUrl": "https://svitprakarsh.github.io/PrakarshGraphics/sponsors/whitehouse.webp",
			"websiteUrl": ""
		},
		{
			"name": "Yuvalay Electronics Lab",
			"description": "",
			"imageUrl": "https://svitprakarsh.github.io/PrakarshGraphics/sponsors/yuva.webp",
			"websiteUrl": "http://elab.yuvalay.org/"
		}
	]
}