{
    "eventName": "Dalal Streets",
    "imageUrl": "",
    "details": [{
            "sectionHeader": "Introduction",
            "sectionContent": "Perfect place where you play with virtual currency."
        },
        {
            "sectionHeader": "Abstract",
            "sectionContent": "If you really wants to challenge your risk taking ability and your luck.This event is absolutely for you."
        },
        {
            "sectionHeader": "Description of Rounds",
            "sectionContent": ""
        },
        {
            "sectionHeader": "Round 1 ",
            "sectionContent": "In this round, the participants have to collect various types of objects from the given location. The objects list will be given on the spot."
        },
        {
            "sectionHeader": "Round 2 ",
            "sectionContent": " In this round, the participant of a team have to blind bet on his/her teammate that the teammate can able to complete the dare."
        },
        {
            "sectionHeader": "Round 3 - ThainThain",
            "sectionContent": " In this round you will be provided with fake cash and you will have to buy fake guns from us. Person who buys the best guns with more money left with him will be the winner"
        },
        {
            "sectionHeader": "Participation",
            "sectionContent": "Individual or Duo"
        },
        {
            "sectionHeader": "Venue & Time",
            "sectionContent": "On 13th Feb,2019:\n  Round 1: C-(313/314) @ 10:45 pm\n  Round 2: C-(313/314) @ 01:15 pm \nOn 14th Feb,2019:\n  Round 3: C-(313/314) @ 10:30 pm\n"
        }
    ],
    "contactDetails": [{
            "name": "Mit Joshi",
            "number": "8140466117"
        },
        {
            "name": "Sankha H. Das",
            "number": "9427003968"
        }
    ]
}